LICENSE.txt
README.md
setup.py
src/super_calc_hacettepe/__init__.py
src/super_calc_hacettepe/add_subtract.py
src/super_calc_hacettepe/multiply_divide.py
src/super_calc_hacettepe/yazilar.txt
src/super_calc_hacettepe.egg-info/PKG-INFO
src/super_calc_hacettepe.egg-info/SOURCES.txt
src/super_calc_hacettepe.egg-info/dependency_links.txt
src/super_calc_hacettepe.egg-info/requires.txt
src/super_calc_hacettepe.egg-info/top_level.txt
src/super_calc_hacettepe/test/yazi.txt