Metadata-Version: 2.1
Name: super-calc-hacettepe
Version: 0.0.25
Summary: Quicksample HACETTEPE
Home-page: UNKNOWN
Author: Atahan Çelebi
License: UNKNOWN
Platform: UNKNOWN
Classifier: Programming Language :: Python :: 3
Classifier: License :: OSI Approved :: MIT License
Classifier: Operating System :: OS Independent
Requires-Python: >=3.6
License-File: LICENSE.txt
